Metadata-Version: 1.2
Name: PySiddhi-ext
Version: 5.1.0.4
Summary: Python wrapper for `Siddhi 5.x.x`.
Home-page: https://github.com/siddhi-io/PySiddhi
Author: WSO2
Author-email: dev@wso2.org
License: Apache2
Platform: UNKNOWN
Classifier: Development Status :: 5 - Production/Stable
Classifier: Intended Audience :: Developers
Classifier: License :: OSI Approved :: Apache Software License
Classifier: Natural Language :: English
Classifier: Operating System :: Microsoft :: Windows
Classifier: Operating System :: POSIX :: Linux
Classifier: Operating System :: MacOS
Classifier: Programming Language :: Python :: 2.7
Classifier: Programming Language :: Python :: 3.3
Classifier: Programming Language :: Python :: 3.4
Classifier: Programming Language :: Python :: 3.5
Classifier: Programming Language :: Python :: 3.6
Classifier: Programming Language :: Python :: 3.7
Classifier: Topic :: Software Development :: Libraries :: Java Libraries
Requires-Python: >=2.7, >=3.6
